gpt3contextual/__init__.py
gpt3contextual/chat.py
gpt3contextual/models.py
gpt3_contextual-0.7.1.dist-info/LICENSE
gpt3_contextual-0.7.1.dist-info/METADATA
gpt3_contextual-0.7.1.dist-info/WHEEL
gpt3_contextual-0.7.1.dist-info/top_level.txt
gpt3_contextual-0.7.1.dist-info/RECORD
