Metadata-Version: 2.1
Name: gpt3-contextual
Version: 0.7.1
Summary: Contextual chat with ChatGPT / GPT-3 of OpenAI API.
Home-page: https://github.com/uezo/gpt3-contextual
Author: uezo
Author-email: uezo@uezo.net
Maintainer: uezo
Maintainer-email: uezo@uezo.net
License: MIT
Classifier: Programming Language :: Python :: 3
License-File: LICENSE
Requires-Dist: openai (==0.27.0)
Requires-Dist: SQLAlchemy (==2.0.4)
